Workbook

Sheet Summary
A2: Family Name | B2: Portfolio Name | C2: Asset Class | D2: Advisors | E2: Asset Name | F2: ISIN
A3: DAJ | B3: AIF | C3: AIF | D3: 360 One | E3: Mt.K Capital Fund Category II
A4: DAJ | B4: Debt MF | C4: Mutual Funds | D4: ARTHYA | E4: BANDHAN Dynamic Bond Fund-Direct Plan-Growth | F4: INF194K01N63
A5: DAJ | B5: Liquid MF | C5: Mutual Funds | D5: KOTAK | E5: Kotak Liquid - Growth - Direct | F5: INF174K01NE8
A6: DAJ | B6: Equity MF | C6: Mutual Funds | D6: ARTHYA | E6: HDFC Focused Fund - Growth Option - Direct Plan | F6: INF179K01VK7
A7: DAJ | B7: Equity MF | C7: Mutual Funds | D7: KOTAK | E7: HDFC Focused Fund - Growth Option - Direct Plan\ | F7: INF179K01VK7
A8: DAJ | B8: CARNELIAN | C8: Equity Stocks | D8: ARTHYA | E8: Aditya Birla Capital | F8: INE674K01013
A9: DAJ | B9: CARNELIAN | C9: Equity Stocks | D9: ARTHYA | E9: Aurobindo Pharma | F9: INE406A01037
A10: DAJ | B10: CARNELIAN | C10: Equity Stocks | D10: ARTHYA | E10: Bharti Airtel | F10: INE397D01024
A11: DAJ | B11: CARNELIAN | C11: Equity Stocks | D11: ARTHYA | E11: Biocon Limited | F11: INE376G01013
A12: DAJ | B12: CARNELIAN | C12: Equity Stocks | D12: ARTHYA | E12: Canara Bank | F12: INE476A01022
A13: DAJ | B13: CARNELIAN | C13: Equity Stocks | D13: ARTHYA | E13: Cyient Limited | F13: INE136B01020
A14: DAJ | B14: CARNELIAN | C14: Equity Stocks | D14: ARTHYA | E14: Dr Lal Pathlabs | F14: INE600L01024
A15: DAJ | B15: CARNELIAN | C15: Equity Stocks | D15: ARTHYA | E15: Endurance Technologies | F15: INE913H01037
... A44: DAJ | B44: InvITs | C44: REITs/InvITs | D44: KOTAK | E44: Cube Highways InvIT | F44: INE0NR623014
A45: DAJ | B45: Unlisted Holdings | C45: Alternate | D45: ARTHYA | E45: Credilio Financial Technologies Private Limited CCPS
A46: DAJ | B46: Bank | C46: Bank | D46: DIRECT | E46: Kotak Savings A/c
A47: DAJ | B47: LRS | C47: LRS | D47: 360 One | E47: Ashoka WhiteOak Emerging Markets Equity Ex India Fund Class A
A51: DJT | B51: BUOYANT | C51: Equity Stocks | D51: 360 One | E51: Archean Chemical Industries | F51: INE128X01021
A52: DJT | B52: BUOYANT | C52: Equity Stocks | D52: 360 One | E52: AXIS Bank | F52: INE238A01034
A53: DJT | B53: BUOYANT | C53: Equity Stocks | D53: 360 One | E53: Bajaj Auto | F53: INE917I01010
A54: DJT | B54: BUOYANT | C54: Equity Stocks | D54: 360 One | E54: Bajaj Finance | F54: INE296A01032
A55: DJT | B55: BUOYANT | C55: Equity Stocks | D55: 360 One | E55: Bharti Airtel | F55: INE397D01024
A56: DJT | B56: BUOYANT | C56: Equity Stocks | D56: 360 One | E56: Britannia Industries | F56: INE216A01030
A57: DJT | B57: BUOYANT | C57: Equity Stocks | D57: 360 One | E57: Dalmia Bharat | F57: INE00R701025
A58: DJT | B58: BUOYANT | C58: Equity Stocks | D58: 360 One | E58: Dilip Buildcon | F58: INE917M01012
A59: DJT | B59: BUOYANT | C59: Equity Stocks | D59: 360 One | E59: Dr. Reddy's Laboratories | F59: INE089A01031
A60: DJT | B60: BUOYANT | C60: Equity Stocks | D60: 360 One | E60: Glenmark Pharmaceuticals | F60: INE935A01035
A61: DJT | B61: BUOYANT | C61: Equity Stocks | D61: 360 One | E61: Granules India | F61: INE101D01020
A62: DJT | B62: BUOYANT | C62: Equity Stocks | D62: 360 One | E62: Hindustan Unilever | F62: INE030A01027
... A81: DJT | B81: BUOYANT | C81: Equity Stocks | D81: 360 One | E81: VIP Industries | F81: INE054A01027
A82: DJT | B82: AIF | C82: AIF | D82: DIRECT | E82: Alchemy Long Term Venture Fund - Series 2
A83: DJT | B83: Debt MF | C83: Mutual Funds | D83: ARTHYA | E83: BANDHAN Dynamic Bond Fund-Direct Plan-Growth | F83: INF194K01N63
A84: DJT | B84: Liquid MF | C84: Mutual Funds | D84: KOTAK | E84: ICICI Prudential Liquid Fund - Direct Plan - Growth | F84: INF109K01Q49
A85: DJT | B85: Equity MF | C85: Mutual Funds | D85: ARTHYA | E85: HDFC Focused Fund - Growth Option - Direct Plan | F85: INF179K01VK7
A86: DJT | B86: Arbitrage MF | C86: Mutual Funds | D86: KOTAK | E86: ICICI Prudential Arbitrage Fund - Direct Plan - Growth | F86: INF109K016O4
A87: DJT | B87: REITs | C87: REITs/InvITs | D87: ARTHYA | E87: Knowledge Realty Trust | F87: INE1JAR25012
A88: DJT | B88: Direct Equity | C88: Equity Stocks | D88: DIRECT | E88: Bajaj Finance | F88: INE296A01032
A89: DJT | B89: Direct Equity | C89: Equity Stocks | D89: DIRECT | E89: Divi's Laboratories | F89: INE361B01024
A90: DJT | B90: Direct Equity | C90: Equity Stocks | D90: DIRECT | E90: HCL Technologies | F90: INE860A01027
A91: DJT | B91: Direct Equity | C91: Equity Stocks | D91: DIRECT | E91: HDFC Life Insurance Company | F91: INE795G01014
A92: DJT | B92: Direct Equity | C92: Equity Stocks | D92: DIRECT | E92: Kotak Mahindra Bank | F92: INE237A01036
A93: DJT | B93: Direct Equity | C93: Equity Stocks | D93: DIRECT | E93: Titan Company | F93: INE280A01028
A94: DJT | B94: Silver ETF | C94: ETF | D94: KOTAK | E94: ICICI Prudential Silver ETF | F94: INF109KC1Y56
A95: DAJ | B95: Bank | C95: Bank | D95: DIRECT | E95: Kotak Current A/C

Sheet Detail
A2: Family Name | B2: Portfolio Name | C2: Asset Class | D2: Advisors | E2: Asset Name | F2: ISIN | G2: Quantity | H2: Avg. Purchase Price | I2: Amount Invested | J2: Current Price | K2: Current Value
A3: DAJ | B3: AIF | C3: AIF | D3: 360 One | E3: Mt.K Capital Fund Category II | G3: 215989.2 | H3: =I3/G3 -> 95.645571 | I3: 20658410 | J3: 126.5739 | K3: 16515153
A4: DAJ | B4: Debt MF | C4: Mutual Funds | D4: ARTHYA | E4: BANDHAN Dynamic Bond Fund-Direct Plan-Growth | F4: INF194K01N63 | G4: 2238333.7 | H4: 31.27 | I4: 70000000 | J4: 40.5573 | K4: 90780772
A5: DAJ | B5: Liquid MF | C5: Mutual Funds | D5: KOTAK | E5: Kotak Liquid - Growth - Direct | F5: INF174K01NE8 | G5: 7523.049 | H5: 5629.13 | I5: 42348194 | J5: 5713.3459 | K5: 42981781
A6: DAJ | B6: Equity MF | C6: Mutual Funds | D6: ARTHYA | E6: HDFC Focused Fund - Growth Option - Direct Plan | F6: INF179K01VK7 | G6: 5091.381 | H6: 267.7 | I6: 1362979.9 | J6: 270.406 | K6: 1376740
A7: DAJ | B7: Equity MF | C7: Mutual Funds | D7: KOTAK | E7: HDFC Focused Fund - Growth Option - Direct Plan\ | F7: INF179K01VK7 | G7: 25771.215 | H7: 268.81 | I7: 6927520.2 | J7: 270.406 | K7: 6968691.2
A8: DAJ | B8: CARNELIAN | C8: Equity Stocks | D8: ARTHYA | E8: Aditya Birla Capital | F8: INE674K01013 | G8: 5803 | H8: 350.11 | I8: 2031691.2 | J8: 396.2 | K8: 2299148.6
A9: DAJ | B9: CARNELIAN | C9: Equity Stocks | D9: ARTHYA | E9: Aurobindo Pharma | F9: INE406A01037 | G9: 433 | H9: 1407.78 | I9: 609568.55 | J9: 1643.7 | K9: 711722.1
A10: DAJ | B10: CARNELIAN | C10: Equity Stocks | D10: ARTHYA | E10: Bharti Airtel | F10: INE397D01024 | G10: 406 | H10: 1966.5 | I10: 798399.98 | J10: 1986.1 | K10: 806356.6
A11: DAJ | B11: CARNELIAN | C11: Equity Stocks | D11: ARTHYA | E11: Biocon Limited | F11: INE376G01013 | G11: 4038 | H11: 358.28 | I11: 1446751.2 | J11: 410.85 | K11: 1659012.3
A12: DAJ | B12: CARNELIAN | C12: Equity Stocks | D12: ARTHYA | E12: Canara Bank | F12: INE476A01022 | G12: 4458 | H12: 138.05 | I12: 615433.86 | J12: 129.8 | K12: 578648.4
A13: DAJ | B13: CARNELIAN | C13: Equity Stocks | D13: ARTHYA | E13: Cyient Limited | F13: INE136B01020 | G13: 119 | H13: 885.11 | I13: 105328.34 | J13: 849.05 | K13: 101036.95
A14: DAJ | B14: CARNELIAN | C14: Equity Stocks | D14: ARTHYA | E14: Dr Lal Pathlabs | F14: INE600L01024 | G14: 515 | H14: 1613.65 | I14: 831030.51 | J14: 1898.9 | K14: 977933.5
A15: DAJ | B15: CARNELIAN | C15: Equity Stocks | D15: ARTHYA | E15: Endurance Technologies | F15: INE913H01037 | G15: 325 | H15: 2391.62 | I15: 777277.83 | J15: 3003 | K15: 975975
... A44: DAJ | B44: InvITs | C44: REITs/InvITs | D44: KOTAK | E44: Cube Highways InvIT | F44: INE0NR623014 | G44: 350000 | H44: 146.19 | I44: 51167034 | J44: 159.89 | K44: 55961500
A45: DAJ | B45: Unlisted Holdings | C45: Alternate | D45: ARTHYA | E45: Credilio Financial Technologies Private Limited CCPS | G45: 83 | H45: 120880 | I45: 10033040 | J45: 120880 | K45: 10033040
A46: DAJ | B46: Bank | C46: Bank | D46: DIRECT | E46: Kotak Savings A/c | I46: 1629616.3 | K46: 1629616.3
A47: DAJ | B47: LRS | C47: LRS | D47: 360 One | E47: Ashoka WhiteOak Emerging Markets Equity Ex India Fund Class A | G47: 1108.805 | H47: 177.22 | I47: 17700413 | J47: 20536.513 | K47: 22770988
A51: DJT | B51: BUOYANT | C51: Equity Stocks | D51: 360 One | E51: Archean Chemical Industries | F51: INE128X01021 | G51: 3169 | H51: 520.92 | I51: 1650780.3 | J51: 511.8 | K51: 1621894.2
A52: DJT | B52: BUOYANT | C52: Equity Stocks | D52: 360 One | E52: AXIS Bank | F52: INE238A01034 | G52: 3480 | H52: 1249.17 | I52: 4347124.6 | J52: 1215.7 | K52: 4230636
A53: DJT | B53: BUOYANT | C53: Equity Stocks | D53: 360 One | E53: Bajaj Auto | F53: INE917I01010 | G53: 142 | H53: 9033.19 | I53: 1282712.9 | J53: 11670 | K53: 1657140
A54: DJT | B54: BUOYANT | C54: Equity Stocks | D54: 360 One | E54: Bajaj Finance | F54: INE296A01032 | G54: 2934 | H54: 879.1 | I54: 2579285 | J54: 1089.8 | K54: 3197473.2
A55: DJT | B55: BUOYANT | C55: Equity Stocks | D55: 360 One | E55: Bharti Airtel | F55: INE397D01024 | G55: 1082 | H55: 1833.2 | I55: 1983518.9 | J55: 1986.1 | K55: 2148960.2
A56: DJT | B56: BUOYANT | C56: Equity Stocks | D56: 360 One | E56: Britannia Industries | F56: INE216A01030 | G56: 300 | H56: 5624.21 | I56: 1687262.9 | J56: 5507 | K56: 1652100
A57: DJT | B57: BUOYANT | C57: Equity Stocks | D57: 360 One | E57: Dalmia Bharat | F57: INE00R701025 | G57: 1058 | H57: 1897.98 | I57: 2008060.6 | J57: 1847 | K57: 1954126
A58: DJT | B58: BUOYANT | C58: Equity Stocks | D58: 360 One | E58: Dilip Buildcon | F58: INE917M01012 | G58: 3630 | H58: 417.96 | I58: 1517177.4 | J58: 412.9 | K58: 1498827
A59: DJT | B59: BUOYANT | C59: Equity Stocks | D59: 360 One | E59: Dr. Reddy's Laboratories | F59: INE089A01031 | G59: 680 | H59: 1319.77 | I59: 897442.94 | J59: 1190.4 | K59: 809472
A60: DJT | B60: BUOYANT | C60: Equity Stocks | D60: 360 One | E60: Glenmark Pharmaceuticals | F60: INE935A01035 | G60: 577 | H60: 2162.8 | I60: 1247935.1 | J60: 2305.4 | K60: 1330215.8
A61: DJT | B61: BUOYANT | C61: Equity Stocks | D61: 360 One | E61: Granules India | F61: INE101D01020 | G61: 2372 | H61: 604.43 | I61: 1433711.4 | J61: 850.25 | K61: 2016793
A62: DJT | B62: BUOYANT | C62: Equity Stocks | D62: 360 One | E62: Hindustan Unilever | F62: INE030A01027 | G62: 940 | H62: 2177.07 | I62: 2046449.8 | J62: 2061 | K62: 1937340
... A81: DJT | B81: BUOYANT | C81: Equity Stocks | D81: 360 One | E81: VIP Industries | F81: INE054A01027 | G81: 2384 | H81: 337.68 | I81: 805019.36 | J81: 295.15 | K81: 703637.6
A82: DJT | B82: AIF | C82: AIF | D82: DIRECT | E82: Alchemy Long Term Venture Fund - Series 2 | G82: 379504.77 | H82: 98.81 | I82: 37498125 | J82: 0 | K82: 37989680
A83: DJT | B83: Debt MF | C83: Mutual Funds | D83: ARTHYA | E83: BANDHAN Dynamic Bond Fund-Direct Plan-Growth | F83: INF194K01N63 | G83: 319761.96 | H83: 31.27 | I83: 10000000 | J83: 40.5573 | K83: 12968682
A84: DJT | B84: Liquid MF | C84: Mutual Funds | D84: KOTAK | E84: ICICI Prudential Liquid Fund - Direct Plan - Growth | F84: INF109K01Q49 | G84: 171419.64 | H84: 411.27 | I84: 70500000 | J84: 418.4641 | K84: 71732966
A85: DJT | B85: Equity MF | C85: Mutual Funds | D85: ARTHYA | E85: HDFC Focused Fund - Growth Option - Direct Plan | F85: INF179K01VK7 | G85: 242899.53 | H85: 223.66 | I85: 54327649 | J85: 270.406 | K85: 65681490
A86: DJT | B86: Arbitrage MF | C86: Mutual Funds | D86: KOTAK | E86: ICICI Prudential Arbitrage Fund - Direct Plan - Growth | F86: INF109K016O4 | G86: 102383.36 | H86: 37.51 | I86: 3839906.9 | J86: 39.4944 | K86: 4043569.3
A87: DJT | B87: REITs | C87: REITs/InvITs | D87: ARTHYA | E87: Knowledge Realty Trust | F87: INE1JAR25012 | G87: 86700 | H87: 99.51 | I87: 8627343.6 | J87: 115.73 | K87: 10033791
A88: DJT | B88: Direct Equity | C88: Equity Stocks | D88: DIRECT | E88: Bajaj Finance | F88: INE296A01032 | G88: 4550 | H88: 600.86 | I88: 2733912.6 | J88: 1089.8 | K88: 4958590
A89: DJT | B89: Direct Equity | C89: Equity Stocks | D89: DIRECT | E89: Divi's Laboratories | F89: INE361B01024 | G89: 637 | H89: 3666.17 | I89: 2335353.1 | J89: 8498 | K89: 5413226
A90: DJT | B90: Direct Equity | C90: Equity Stocks | D90: DIRECT | E90: HCL Technologies | F90: INE860A01027 | G90: 2620 | H90: 956.05 | I90: 2504849 | J90: 1334.4 | K90: 3496128
A91: DJT | B91: Direct Equity | C91: Equity Stocks | D91: DIRECT | E91: HDFC Life Insurance Company | F91: INE795G01014 | G91: 2668 | H91: 669.18 | I91: 1785372.8 | J91: 541.8 | K91: 1445522.4
A92: DJT | B92: Direct Equity | C92: Equity Stocks | D92: DIRECT | E92: Kotak Mahindra Bank | F92: INE237A01036 | G92: 2910 | H92: 346.81 | I92: 1009206.3 | J92: 392.35 | K92: 1141738.5
A93: DJT | B93: Direct Equity | C93: Equity Stocks | D93: DIRECT | E93: Titan Company | F93: INE280A01028 | G93: 1047 | H93: 1734.67 | I93: 1816197.9 | J93: 5071.8 | K93: 5310174.6
A94: DJT | B94: Silver ETF | C94: ETF | D94: KOTAK | E94: ICICI Prudential Silver ETF | F94: INF109KC1Y56 | G94: 193700 | H94: 129.16 | I94: 25018622 | J94: 233.89 | K94: 45304493
A95: DAJ | B95: Bank | C95: Bank | D95: DIRECT | E95: Kotak Current A/C | I95: 356709 | K95: 356709

Sheet Transactions
A1: Family Name | B1: Asset Class | C1: Sub Class | D1: Asset Name | E1: Underlying | F1: Advisors | G1: ISIN | H1: Date | I1: Trans. Type | J1: Quantity | K1: Price | L1: Amount
A2: DAJ | B2: Equity | C2: Equity PMS | D2: Carnelian Capital Compounder Strategy | E2: Bharti Airtel | F2: ARTHYA | G2: =+VLOOKUP(E2,Summary!$E$3:$F$47,2,0) -> INE397D01024 | H2: 46239 | I2: Buy | J2: 198 | K2: 1969.9533 | L2: 390323.79
A3: DAJ | B3: Equity | C3: Equity PMS | D3: Carnelian Capital Compounder Strategy | E3: Bharti Airtel | F3: ARTHYA | G3: =+VLOOKUP(E3,Summary!$E$3:$F$47,2,0) -> INE397D01024 | H3: 46234 | I3: Buy | J3: 208 | K3: 1960.9243 | L3: 408076.19
A4: DAJ | B4: Equity | C4: Equity PMS | D4: Carnelian Capital Compounder Strategy | E4: Delhivery | F4: ARTHYA | G4: INE148O01028 | H4: 46234 | I4: Sell | J4: 278 | K4: 476.5 | L4: 132400.78
A5: DAJ | B5: Equity | C5: Equity PMS | D5: Carnelian Capital Compounder Strategy | E5: Delhivery | F5: ARTHYA | G5: INE148O01028 | H5: 46232 | I5: Sell | J5: 626 | K5: 472.7459 | L5: 295791.01
A6: DAJ | B6: Equity | C6: Equity PMS | D6: Carnelian Capital Compounder Strategy | E6: Sun Pharmaceutical | F6: ARTHYA | G6: =+VLOOKUP(E6,Summary!$E$3:$F$47,2,0) -> INE044A01036 | H6: 46232 | I6: Buy | J6: 34 | K6: 1970.9938 | L6: 67047.29
A7: DAJ | B7: Equity | C7: Equity PMS | D7: Carnelian Capital Compounder Strategy | E7: Sun Pharmaceutical | F7: ARTHYA | G7: =+VLOOKUP(E7,Summary!$E$3:$F$47,2,0) -> INE044A01036 | H7: 46231 | I7: Buy | J7: 89 | K7: 1984.6671 | L7: 176723.68
A8: DAJ | B8: Equity | C8: Equity PMS | D8: Carnelian Capital Compounder Strategy | E8: Pidilite Industries | F8: ARTHYA | G8: INE318A01026 | H8: 46230 | I8: Sell | J8: 151 | K8: 1596 | L8: 240876.26
A9: DAJ | B9: Equity | C9: Equity PMS | D9: Carnelian Capital Compounder Strategy | E9: Sun Pharmaceutical | F9: ARTHYA | G9: =+VLOOKUP(E9,Summary!$E$3:$F$47,2,0) -> INE044A01036 | H9: 46230 | I9: Buy | J9: 193 | K9: 1974.5437 | L9: 381277.46
A10: DAJ | B10: Equity | C10: Equity PMS | D10: Carnelian Capital Compounder Strategy | E10: Dr Lal Pathlabs | F10: ARTHYA | G10: =+VLOOKUP(E10,Summary!$E$3:$F$47,2,0) -> INE600L01024 | H10: 46227 | I10: Buy | J10: 14 | K10: 1722.4807 | L10: 24126.79
A11: DAJ | B11: Equity | C11: Equity PMS | D11: Carnelian Capital Compounder Strategy | E11: Pidilite Industries | F11: ARTHYA | G11: INE318A01026 | H11: 46227 | I11: Sell | J11: 285 | K11: 1570.5679 | L11: 447388.04
A12: DAJ | B12: Equity | C12: Equity PMS | D12: Carnelian Capital Compounder Strategy | E12: Bandhan Bank | F12: ARTHYA | G12: INE545U01014 | H12: 46226 | I12: Sell | J12: 861 | K12: 167.7673 | L12: 144346.53
A13: DAJ | B13: Equity | C13: Equity PMS | D13: Carnelian Capital Compounder Strategy | E13: Bandhan Bank | F13: ARTHYA | G13: INE545U01014 | H13: 46225 | I13: Sell | J13: 1081 | K13: 182.0485 | L13: 196696.05
A14: DAJ | B14: Equity | C14: Equity PMS | D14: Carnelian Capital Compounder Strategy | E14: Kalyan Jewellers India | F14: ARTHYA | G14: =+VLOOKUP(E14,Summary!$E$3:$F$47,2,0) -> INE303R01014 | H14: 46216 | I14: Buy | J14: 512 | K14: 500.0107 | L14: 256261.48
A15: DAJ | B15: Equity | C15: Equity PMS | D15: Carnelian Capital Compounder Strategy | E15: Tata Technologies | F15: ARTHYA | G15: =+VLOOKUP(E15,Summary!$E$3:$F$47,2,0) -> INE142M01025 | H15: 46212 | I15: Buy | J15: 150 | K15: 715.097 | L15: 107318.18
A16: DAJ | B16: Equity | C16: Equity PMS | D16: Carnelian Capital Compounder Strategy | E16: Cyient Limited | F16: ARTHYA | G16: =+VLOOKUP(E16,Summary!$E$3:$F$47,2,0) -> INE136B01020 | H16: 46210 | I16: Sell | J16: 37 | K16: 1125 | L16: 41562.19
A17: DAJ | B17: Equity | C17: Equity PMS | D17: Carnelian Capital Compounder Strategy | E17: Persistent Systems | F17: ARTHYA | G17: =+VLOOKUP(E17,Summary!$E$3:$F$47,2,0) -> INE262H01021 | H17: 46206 | I17: Buy | J17: 68 | K17: 4684.9996 | L17: 318898.55
A18: DAJ | B18: Equity | C18: Equity PMS | D18: Carnelian Capital Compounder Strategy | E18: Larsen & Toubro | F18: ARTHYA | G18: =+VLOOKUP(E18,Summary!$E$3:$F$47,2,0) -> INE018A01030 | H18: 46189 | I18: Buy | J18: 41 | K18: 4221.54 | L18: 173169.76
A19: DAJ | B19: Equity | C19: Equity PMS | D19: Carnelian Capital Compounder Strategy | E19: Tata Technologies | F19: ARTHYA | G19: =+VLOOKUP(E19,Summary!$E$3:$F$47,2,0) -> INE142M01025 | H19: 46188 | I19: Buy | J19: 513 | K19: 770.2931 | L19: 395357.92
A20: DAJ | B20: Equity | C20: Equity PMS | D20: Carnelian Capital Compounder Strategy | E20: Canara Bank | F20: ARTHYA | G20: =+VLOOKUP(E20,Summary!$E$3:$F$47,2,0) -> INE476A01022 | H20: 46185 | I20: Buy | J20: 71 | K20: 131.6137 | L20: 9349.24
A21: DAJ | B21: Equity | C21: Equity PMS | D21: Carnelian Capital Compounder Strategy | E21: Delhivery | F21: ARTHYA | G21: INE148O01028 | H21: 46185 | I21: Buy | J21: 15 | K21: 440.912 | L21: 6616.99
A22: DAJ | B22: Equity | C22: Equity PMS | D22: Carnelian Capital Compounder Strategy | E22: Larsen & Toubro | F22: ARTHYA | G22: =+VLOOKUP(E22,Summary!$E$3:$F$47,2,0) -> INE018A01030 | H22: 46185 | I22: Buy | J22: 4 | K22: 4043.0325 | L22: 16180.22
A23: DAJ | B23: Equity | C23: Equity PMS | D23: Carnelian Capital Compounder Strategy | E23: LTM Limited | F23: ARTHYA | G23: =+VLOOKUP(E23,Summary!$E$3:$F$47,2,0) -> INE214T01019 | H23: 46185 | I23: Buy | J23: 5 | K23: 3841.962 | L23: 19219.41
A24: DAJ | B24: Equity | C24: Equity PMS | D24: Carnelian Capital Compounder Strategy | E24: Max Financial Services | F24: ARTHYA | G24: =+VLOOKUP(E24,Summary!$E$3:$F$47,2,0) -> INE180A01020 | H24: 46185 | I24: Buy | J24: 16 | K24: 1577.1131 | L24: 25246.43
A25: DAJ | B25: Equity | C25: Equity PMS | D25: Carnelian Capital Compounder Strategy | E25: One 97 Communications | F25: ARTHYA | G25: =+VLOOKUP(E25,Summary!$E$3:$F$47,2,0) -> INE982J01020 | H25: 46185 | I25: Buy | J25: 44 | K25: 1073.1866 | L25: 47243.82
A26: DAJ | B26: Equity | C26: Equity PMS | D26: Carnelian Capital Compounder Strategy | E26: Tata Motors | F26: ARTHYA | G26: =+VLOOKUP(E26,Summary!$E$3:$F$47,2,0) -> INE1TAE01010 | H26: 46185 | I26: Buy | J26: 77 | K26: 389.1997 | L26: 29983.36
A27: DAJ | B27: Equity | C27: Equity PMS | D27: Carnelian Capital Compounder Strategy | E27: Tata Motors Passenger Vehicles | F27: ARTHYA | G27: =+VLOOKUP(E27,Summary!$E$3:$F$47,2,0) -> INE155A01022 | H27: 46185 | I27: Buy | J27: 37 | K27: 389.4824 | L27: 14418.05
A28: DAJ | B28: Equity | C28: Equity PMS | D28: Carnelian Capital Compounder Strategy | E28: Tata Technologies | F28: ARTHYA | G28: =+VLOOKUP(E28,Summary!$E$3:$F$47,2,0) -> INE142M01025 | H28: 46185 | I28: Buy | J28: 23 | K28: 760.94 | L28: 17510.37
A29: DAJ | B29: Equity | C29: Equity PMS | D29: Carnelian Capital Compounder Strategy | E29: Tata Technologies | F29: ARTHYA | G29: =+VLOOKUP(E29,Summary!$E$3:$F$47,2,0) -> INE142M01025 | H29: 46184 | I29: Buy | J29: 247 | K29: 745.9687 | L29: 184383.25
A30: DAJ | B30: Equity | C30: Equity PMS | D30: Carnelian Capital Compounder Strategy | E30: Tata Motors | F30: ARTHYA | G30: =+VLOOKUP(E30,Summary!$E$3:$F$47,2,0) -> INE1TAE01010 | H30: 46183 | I30: Buy | J30: 32 | K30: 365.7287 | L30: 11709.17
A31: DAJ | B31: Equity | C31: Equity PMS | D31: Carnelian Capital Compounder Strategy | E31: Tata Technologies | F31: ARTHYA | G31: =+VLOOKUP(E31,Summary!$E$3:$F$47,2,0) -> INE142M01025 | H31: 46183 | I31: Buy | J31: 531 | K31: 757.6995 | L31: 402579.83
A32: DAJ | B32: Equity | C32: Equity PMS | D32: Carnelian Capital Compounder Strategy | E32: GlaxoSmithkline Pharmaceuticals | F32: ARTHYA | G32: INE159A01016 | H32: 46177 | I32: Sell | J32: 85 | K32: 2167.2117 | L32: 184102.46
A33: DAJ | B33: Equity | C33: Equity PMS | D33: Carnelian Capital Compounder Strategy | E33: Tata Motors Passenger Vehicles | F33: ARTHYA | G33: =+VLOOKUP(E33,Summary!$E$3:$F$47,2,0) -> INE155A01022 | H33: 46177 | I33: Buy | J33: 742 | K33: 398.4586 | L33: 295804.1
A34: DAJ | B34: Equity | C34: Equity PMS | D34: Carnelian Capital Compounder Strategy | E34: Maruti Suzuki | F34: ARTHYA | G34: INE585B01010 | H34: 46176 | I34: Sell | J34: 44 | K34: 13100.975 | L34: 576097.03
A35: DAJ | B35: Equity | C35: Equity PMS | D35: Carnelian Capital Compounder Strategy | E35: LTM Limited | F35: ARTHYA | G35: =+VLOOKUP(E35,Summary!$E$3:$F$47,2,0) -> INE214T01019 | H35: 46174 | I35: Buy | J35: 46 | K35: 4245.5452 | L35: 195392.73
A36: DAJ | B36: Equity | C36: Equity PMS | D36: Carnelian Capital Compounder Strategy | E36: Poly Medicure | F36: ARTHYA | G36: =+VLOOKUP(E36,Summary!$E$3:$F$47,2,0) -> INE205C01021 | H36: 46174 | I36: Buy | J36: 15 | K36: 1342.0962 | L36: 20141.51
A37: DAJ | B37: Equity | C37: Equity PMS | D37: Carnelian Capital Compounder Strategy | E37: GlaxoSmithkline Pharmaceuticals | F37: ARTHYA | G37: INE159A01016 | H37: 46169 | I37: Sell | J37: 46 | K37: 2307.0193 | L37: 106069.83
A38: DAJ | B38: Equity | C38: Equity PMS | D38: Carnelian Capital Compounder Strategy | E38: Aurobindo Pharma | F38: ARTHYA | G38: =+VLOOKUP(E38,Summary!$E$3:$F$47,2,0) -> INE406A01037 | H38: 46168 | I38: Buy | J38: 2 | K38: 1455.355 | L38: 2912.17
A39: DAJ | B39: Equity | C39: Equity PMS | D39: Carnelian Capital Compounder Strategy | E39: Delhivery | F39: ARTHYA | G39: INE148O01028 | H39: 46168 | I39: Buy | J39: 489 | K39: 458.8489 | L39: 224489.29
A40: DAJ | B40: Equity | C40: Equity PMS | D40: Carnelian Capital Compounder Strategy | E40: Dr Lal Pathlabs | F40: ARTHYA | G40: =+VLOOKUP(E40,Summary!$E$3:$F$47,2,0) -> INE600L01024 | H40: 46168 | I40: Buy | J40: 3 | K40: 1618.33 | L40: 4858.07
A41: DAJ | B41: Equity | C41: Equity PMS | D41: Carnelian Capital Compounder Strategy | E41: Interglobe Aviation | F41: ARTHYA | G41: =+VLOOKUP(E41,Summary!$E$3:$F$47,2,0) -> INE646L01027 | H41: 46168 | I41: Buy | J41: 70 | K41: 4480.9556 | L41: 313823.72
A42: DAJ | B42: Equity | C42: Equity PMS | D42: Carnelian Capital Compounder Strategy | E42: LTM Limited | F42: ARTHYA | G42: =+VLOOKUP(E42,Summary!$E$3:$F$47,2,0) -> INE214T01019 | H42: 46168 | I42: Buy | J42: 17 | K42: 3985.16 | L42: 67781.63
A43: DAJ | B43: Equity | C43: Equity PMS | D43: Carnelian Capital Compounder Strategy | E43: One 97 Communications | F43: ARTHYA | G43: =+VLOOKUP(E43,Summary!$E$3:$F$47,2,0) -> INE982J01020 | H43: 46168 | I43: Buy | J43: 2 | K43: 1123.305 | L43: 2247.73
A44: DAJ | B44: Equity | C44: Equity PMS | D44: Carnelian Capital Compounder Strategy | E44: Pidilite Industries | F44: ARTHYA | G44: INE318A01026 | H44: 46168 | I44: Buy | J44: 10 | K44: 1470.469 | L44: 14712.04
A45: DAJ | B45: Equity | C45: Equity PMS | D45: Carnelian Capital Compounder Strategy | E45: Star Health & Allied Insurance Company | F45: ARTHYA | G45: =+VLOOKUP(E45,Summary!$E$3:$F$47,2,0) -> INE575P01011 | H45: 46168 | I45: Buy | J45: 367 | K45: 530.6099 | L45: 194831.2
A46: DAJ | B46: Equity | C46: Equity PMS | D46: Carnelian Capital Compounder Strategy | E46: Tata Motors | F46: ARTHYA | G46: =+VLOOKUP(E46,Summary!$E$3:$F$47,2,0) -> INE1TAE01010 | H46: 46168 | I46: Buy | J46: 116 | K46: 386.01 | L46: 44800.11
A47: DAJ | B47: Equity | C47: Equity PMS | D47: Carnelian Capital Compounder Strategy | E47: Gland Pharma | F47: ARTHYA | G47: =+VLOOKUP(E47,Summary!$E$3:$F$47,2,0) -> INE068V01023 | H47: 46164 | I47: Buy | J47: 13 | K47: 2329.9908 | L47: 30305.02
A48: DAJ | B48: Equity | C48: Equity PMS | D48: Carnelian Capital Compounder Strategy | E48: Gland Pharma | F48: ARTHYA | G48: =+VLOOKUP(E48,Summary!$E$3:$F$47,2,0) -> INE068V01023 | H48: 46163 | I48: Buy | J48: 245 | K48: 2339.03 | L48: 573352.52
A49: DAJ | B49: Equity | C49: Equity PMS | D49: Carnelian Capital Compounder Strategy | E49: GlaxoSmithkline Pharmaceuticals | F49: ARTHYA | G49: INE159A01016 | H49: 46163 | I49: Sell | J49: 46 | K49: 2320.4239 | L49: 106686.13
A50: DAJ | B50: Equity | C50: Equity PMS | D50: Carnelian Capital Compounder Strategy | E50: Page Industries | F50: ARTHYA | G50: =+VLOOKUP(E50,Summary!$E$3:$F$47,2,0) -> INE761H01022 | H50: 46163 | I50: Buy | J50: 8 | K50: 37975.213 | L50: 303983.98
A51: DAJ | B51: Equity | C51: Equity PMS | D51: Carnelian Capital Compounder Strategy | E51: United Spirits | F51: ARTHYA | G51: INE854D01024 | H51: 46163 | I51: Sell | J51: 30 | K51: 1285.089 | L51: 38533.4
A52: DAJ | B52: Equity | C52: Equity PMS | D52: Carnelian Capital Compounder Strategy | E52: GlaxoSmithkline Pharmaceuticals | F52: ARTHYA | G52: INE159A01016 | H52: 46162 | I52: Sell | J52: 25 | K52: 2358.554 | L52: 58934.37
A53: DAJ | B53: Equity | C53: Equity PMS | D53: Carnelian Capital Compounder Strategy | E53: United Spirits | F53: ARTHYA | G53: INE854D01024 | H53: 46162 | I53: Sell | J53: 510 | K53: 1284.5302 | L53: 654651.81
A54: DAJ | B54: Equity | C54: Equity PMS | D54: Carnelian Capital Compounder Strategy | E54: Page Industries | F54: ARTHYA | G54: =+VLOOKUP(E54,Summary!$E$3:$F$47,2,0) -> INE761H01022 | H54: 46160 | I54: Buy | J54: 15 | K54: 37358.64 | L54: 560659.82
A55: DAJ | B55: Equity | C55: Equity PMS | D55: Carnelian Capital Compounder Strategy | E55: Punjab National Bank | F55: ARTHYA | G55: INE160A01022 | H55: 46160 | I55: Sell | J55: 4106 | K55: 99.4636 | L55: 408193.47
A56: DAJ | B56: Equity | C56: Equity PMS | D56: Carnelian Capital Compounder Strategy | E56: Dr Lal Pathlabs | F56: ARTHYA | G56: =+VLOOKUP(E56,Summary!$E$3:$F$47,2,0) -> INE600L01024 | H56: 46157 | I56: Buy | J56: 498 | K56: 1609.7286 | L56: 802045.65
A57: DAJ | B57: Equity | C57: Equity PMS | D57: Carnelian Capital Compounder Strategy | E57: Page Industries | F57: ARTHYA | G57: =+VLOOKUP(E57,Summary!$E$3:$F$47,2,0) -> INE761H01022 | H57: 46157 | I57: Buy | J57: 3 | K57: 36620.365 | L57: 109916.02
A58: DAJ | B58: Equity | C58: Equity PMS | D58: Carnelian Capital Compounder Strategy | E58: Poly Medicure | F58: ARTHYA | G58: =+VLOOKUP(E58,Summary!$E$3:$F$47,2,0) -> INE205C01021 | H58: 46157 | I58: Buy | J58: 22 | K58: 1504.7329 | L58: 33120.67
A59: DAJ | B59: Equity | C59: Equity PMS | D59: Carnelian Capital Compounder Strategy | E59: Punjab National Bank | F59: ARTHYA | G59: INE160A01022 | H59: 46157 | I59: Sell | J59: 2695 | K59: 102.6132 | L59: 276404.32
A60: DAJ | B60: Equity | C60: Equity PMS | D60: Carnelian Capital Compounder Strategy | E60: Canara Bank | F60: ARTHYA | G60: =+VLOOKUP(E60,Summary!$E$3:$F$47,2,0) -> INE476A01022 | H60: 46156 | I60: Buy | J60: 77 | K60: 130.5993 | L60: 10061.18
A61: DAJ | B61: Equity | C61: Equity PMS | D61: Carnelian Capital Compounder Strategy | E61: Cyient Limited | F61: ARTHYA | G61: =+VLOOKUP(E61,Summary!$E$3:$F$47,2,0) -> INE136B01020 | H61: 46156 | I61: Buy | J61: 66 | K61: 878.4753 | L61: 58008.36
A62: DAJ | B62: Equity | C62: Equity PMS | D62: Carnelian Capital Compounder Strategy | E62: Delhivery | F62: ARTHYA | G62: INE148O01028 | H62: 46156 | I62: Buy | J62: 167 | K62: 469.344 | L62: 78419.64
A63: DAJ | B63: Equity | C63: Equity PMS | D63: Carnelian Capital Compounder Strategy | E63: GlaxoSmithkline Pharmaceuticals | F63: ARTHYA | G63: INE159A01016 | H63: 46156 | I63: Buy | J63: 69 | K63: 2417.6648 | L63: 166902.28
A64: DAJ | B64: Equity | C64: Equity PMS | D64: Carnelian Capital Compounder Strategy | E64: ICICI Bank | F64: ARTHYA | G64: =+VLOOKUP(E64,Summary!$E$3:$F$47,2,0) -> INE090A01021 | H64: 46156 | I64: Buy | J64: 3 | K64: 1252.1333 | L64: 3758.28
A65: DAJ | B65: Equity | C65: Equity PMS | D65: Carnelian Capital Compounder Strategy | E65: Interglobe Aviation | F65: ARTHYA | G65: =+VLOOKUP(E65,Summary!$E$3:$F$47,2,0) -> INE646L01027 | H65: 46156 | I65: Buy | J65: 27 | K65: 4282.1741 | L65: 115676.51
A66: DAJ | B66: Equity | C66: Equity PMS | D66: Carnelian Capital Compounder Strategy | E66: Larsen & Toubro | F66: ARTHYA | G66: =+VLOOKUP(E66,Summary!$E$3:$F$47,2,0) -> INE018A01030 | H66: 46156 | I66: Buy | J66: 2 | K66: 3965.75 | L66: 7935.47
A67: DAJ | B67: Equity | C67: Equity PMS | D67: Carnelian Capital Compounder Strategy | E67: LTM Limited | F67: ARTHYA | G67: =+VLOOKUP(E67,Summary!$E$3:$F$47,2,0) -> INE214T01019 | H67: 46156 | I67: Buy | J67: 2 | K67: 3954.45 | L67: 7912.85
A68: DAJ | B68: Equity | C68: Equity PMS | D68: Carnelian Capital Compounder Strategy | E68: Max Financial Services | F68: ARTHYA | G68: =+VLOOKUP(E68,Summary!$E$3:$F$47,2,0) -> INE180A01020 | H68: 46156 | I68: Buy | J68: 3 | K68: 1632.1767 | L68: 4898.98
A69: DAJ | B69: Equity | C69: Equity PMS | D69: Carnelian Capital Compounder Strategy | E69: Poly Medicure | F69: ARTHYA | G69: =+VLOOKUP(E69,Summary!$E$3:$F$47,2,0) -> INE205C01021 | H69: 46156 | I69: Buy | J69: 371 | K69: 1524.5751 | L69: 565956.71
A70: DAJ | B70: Equity | C70: Equity PMS | D70: Carnelian Capital Compounder Strategy | E70: Punjab National Bank | F70: ARTHYA | G70: INE160A01022 | H70: 46156 | I70: Buy | J70: 121 | K70: 104.1864 | L70: 12612.85
A71: DAJ | B71: Equity | C71: Equity PMS | D71: Carnelian Capital Compounder Strategy | E71: Star Health & Allied Insurance Company | F71: ARTHYA | G71: =+VLOOKUP(E71,Summary!$E$3:$F$47,2,0) -> INE575P01011 | H71: 46156 | I71: Buy | J71: 4 | K71: 508.3825 | L71: 2034.55
A72: DAJ | B72: Equity | C72: Equity PMS | D72: Carnelian Capital Compounder Strategy | E72: Tata Motors | F72: ARTHYA | G72: =+VLOOKUP(E72,Summary!$E$3:$F$47,2,0) -> INE1TAE01010 | H72: 46156 | I72: Buy | J72: 44 | K72: 380.2736 | L72: 16740.41
A73: DAJ | B73: Equity | C73: Equity PMS | D73: Carnelian Capital Compounder Strategy | E73: Tech Mahindra | F73: ARTHYA | G73: =+VLOOKUP(E73,Summary!$E$3:$F$47,2,0) -> INE669C01036 | H73: 46156 | I73: Buy | J73: 4 | K73: 1333.42 | L73: 5336.35
A74: DAJ | B74: Equity | C74: Equity PMS | D74: Carnelian Capital Compounder Strategy | E74: United Spirits | F74: ARTHYA | G74: INE854D01024 | H74: 46156 | I74: Buy | J74: 9 | K74: 1268.76 | L74: 11424.55
A75: DAJ | B75: Equity | C75: Equity PMS | D75: Carnelian Capital Compounder Strategy | E75: Canara Bank | F75: ARTHYA | G75: =+VLOOKUP(E75,Summary!$E$3:$F$47,2,0) -> INE476A01022 | H75: 46154 | I75: Buy | J75: 128 | K75: 130.4948 | L75: 16711.68
A76: DAJ | B76: Equity | C76: Equity PMS | D76: Carnelian Capital Compounder Strategy | E76: Cyient Limited | F76: ARTHYA | G76: =+VLOOKUP(E76,Summary!$E$3:$F$47,2,0) -> INE136B01020 | H76: 46154 | I76: Buy | J76: 90 | K76: 892.3837 | L76: 80354.69
A77: DAJ | B77: Equity | C77: Equity PMS | D77: Carnelian Capital Compounder Strategy | E77: Delhivery | F77: ARTHYA | G77: INE148O01028 | H77: 46154 | I77: Buy | J77: 233 | K77: 470.8503 | L77: 109762.97
A78: DAJ | B78: Equity | C78: Equity PMS | D78: Carnelian Capital Compounder Strategy | E78: GlaxoSmithkline Pharmaceuticals | F78: ARTHYA | G78: INE159A01016 | H78: 46154 | I78: Buy | J78: 133 | K78: 2462.8453 | L78: 327722.2
A79: DAJ | B79: Equity | C79: Equity PMS | D79: Carnelian Capital Compounder Strategy | E79: Interglobe Aviation | F79: ARTHYA | G79: =+VLOOKUP(E79,Summary!$E$3:$F$47,2,0) -> INE646L01027 | H79: 46154 | I79: Buy | J79: 38 | K79: 4241.6866 | L79: 161264.68
A80: DAJ | B80: Equity | C80: Equity PMS | D80: Carnelian Capital Compounder Strategy | E80: Larsen & Toubro | F80: ARTHYA | G80: =+VLOOKUP(E80,Summary!$E$3:$F$47,2,0) -> INE018A01030 | H80: 46154 | I80: Buy | J80: 4 | K80: 3892.655 | L80: 15578.41
A81: DAJ | B81: Equity | C81: Equity PMS | D81: Carnelian Capital Compounder Strategy | E81: LG Electronics India | F81: ARTHYA | G81: =+VLOOKUP(E81,Summary!$E$3:$F$47,2,0) -> INE324D01010 | H81: 46154 | I81: Buy | J81: 38 | K81: 1493.4958 | L81: 56781.23
A82: DAJ | B82: Equity | C82: Equity PMS | D82: Carnelian Capital Compounder Strategy | E82: Punjab National Bank | F82: ARTHYA | G82: INE160A01022 | H82: 46154 | I82: Buy | J82: 155 | K82: 103.1448 | L82: 15995.42
A83: DAJ | B83: Equity | C83: Equity PMS | D83: Carnelian Capital Compounder Strategy | E83: Tata Motors | F83: ARTHYA | G83: =+VLOOKUP(E83,Summary!$E$3:$F$47,2,0) -> INE1TAE01010 | H83: 46154 | I83: Buy | J83: 24 | K83: 398.1263 | L83: 9559.81
A84: DAJ | B84: Equity | C84: Equity PMS | D84: Carnelian Capital Compounder Strategy | E84: United Spirits | F84: ARTHYA | G84: INE854D01024 | H84: 46154 | I84: Buy | J84: 18 | K84: 1254.8328 | L84: 22598.28
A85: DAJ | B85: Equity | C85: Equity PMS | D85: Carnelian Capital Compounder Strategy | E85: ICICI Bank | F85: ARTHYA | G85: =+VLOOKUP(E85,Summary!$E$3:$F$47,2,0) -> INE090A01021 | H85: 46149 | I85: Buy | J85: 35 | K85: 1282.9349 | L85: 44947.62
A86: DAJ | B86: Equity | C86: Equity PMS | D86: Carnelian Capital Compounder Strategy | E86: Larsen & Toubro | F86: ARTHYA | G86: =+VLOOKUP(E86,Summary!$E$3:$F$47,2,0) -> INE018A01030 | H86: 46149 | I86: Buy | J86: 5 | K86: 4032.854 | L86: 20184.43
A87: DAJ | B87: Equity | C87: Equity PMS | D87: Carnelian Capital Compounder Strategy | E87: Canara Bank | F87: ARTHYA | G87: =+VLOOKUP(E87,Summary!$E$3:$F$47,2,0) -> INE476A01022 | H87: 46142 | I87: Buy | J87: 509 | K87: 133.9008 | L87: 68189.56
A88: DAJ | B88: Equity | C88: Equity PMS | D88: Carnelian Capital Compounder Strategy | E88: Larsen & Toubro | F88: ARTHYA | G88: =+VLOOKUP(E88,Summary!$E$3:$F$47,2,0) -> INE018A01030 | H88: 46142 | I88: Buy | J88: 20 | K88: 3998.944 | L88: 80018.87
A89: DAJ | B89: Equity | C89: Equity PMS | D89: Carnelian Capital Compounder Strategy | E89: Max Financial Services | F89: ARTHYA | G89: =+VLOOKUP(E89,Summary!$E$3:$F$47,2,0) -> INE180A01020 | H89: 46142 | I89: Buy | J89: 40 | K89: 1584.5787 | L89: 63414.84
A90: DAJ | B90: Equity | C90: Equity PMS | D90: Carnelian Capital Compounder Strategy | E90: Canara Bank | F90: ARTHYA | G90: =+VLOOKUP(E90,Summary!$E$3:$F$47,2,0) -> INE476A01022 | H90: 46141 | I90: Buy | J90: 631 | K90: 137.7849 | L90: 86985.75
A91: DAJ | B91: Equity | C91: Equity PMS | D91: Carnelian Capital Compounder Strategy | E91: Endurance Technologies | F91: ARTHYA | G91: =+VLOOKUP(E91,Summary!$E$3:$F$47,2,0) -> INE913H01037 | H91: 46141 | I91: Buy | J91: 10 | K91: 2353.251 | L91: 23544.28
A92: DAJ | B92: Equity | C92: Equity PMS | D92: Carnelian Capital Compounder Strategy | E92: ICICI Bank | F92: ARTHYA | G92: =+VLOOKUP(E92,Summary!$E$3:$F$47,2,0) -> INE090A01021 | H92: 46141 | I92: Buy | J92: 17 | K92: 1286.7624 | L92: 21885.9
A93: DAJ | B93: Equity | C93: Equity PMS | D93: Carnelian Capital Compounder Strategy | E93: Larsen & Toubro | F93: ARTHYA | G93: =+VLOOKUP(E93,Summary!$E$3:$F$47,2,0) -> INE018A01030 | H93: 46141 | I93: Buy | J93: 27 | K93: 4113.7259 | L93: 111126.14
A94: DAJ | B94: Equity | C94: Equity PMS | D94: Carnelian Capital Compounder Strategy | E94: LTM Limited | F94: ARTHYA | G94: =+VLOOKUP(E94,Summary!$E$3:$F$47,2,0) -> INE214T01019 | H94: 46141 | I94: Buy | J94: 1 | K94: 4328 | L94: 4330.16
A95: DAJ | B95: Equity | C95: Equity PMS | D95: Carnelian Capital Compounder Strategy | E95: Max Financial Services | F95: ARTHYA | G95: =+VLOOKUP(E95,Summary!$E$3:$F$47,2,0) -> INE180A01020 | H95: 46141 | I95: Buy | J95: 50 | K95: 1607.8056 | L95: 80430.47
A96: DAJ | B96: Equity | C96: Equity PMS | D96: Carnelian Capital Compounder Strategy | E96: Pidilite Industries | F96: ARTHYA | G96: INE318A01026 | H96: 46141 | I96: Buy | J96: 117 | K96: 1395.8107 | L96: 163391.5
A97: DAJ | B97: Equity | C97: Equity PMS | D97: Carnelian Capital Compounder Strategy | E97: Punjab National Bank | F97: ARTHYA | G97: INE160A01022 | H97: 46141 | I97: Buy | J97: 41 | K97: 111.9039 | L97: 4590.35
A98: DAJ | B98: Equity | C98: Equity PMS | D98: Carnelian Capital Compounder Strategy | E98: Tata Motors | F98: ARTHYA | G98: =+VLOOKUP(E98,Summary!$E$3:$F$47,2,0) -> INE1TAE01010 | H98: 46141 | I98: Buy | J98: 35 | K98: 417.5806 | L98: 14622.63
A99: DAJ | B99: Equity | C99: Equity PMS | D99: Carnelian Capital Compounder Strategy | E99: Tech Mahindra | F99: ARTHYA | G99: =+VLOOKUP(E99,Summary!$E$3:$F$47,2,0) -> INE669C01036 | H99: 46141 | I99: Buy | J99: 5 | K99: 1459.482 | L99: 7301.06
A100: DAJ | B100: Equity | C100: Equity PMS | D100: Carnelian Capital Compounder Strategy | E100: Bandhan Bank | F100: ARTHYA | G100: INE545U01014 | H100: 46140 | I100: Buy | J100: 242 | K100: 180.2386 | L100: 43639.54
...
